{
  "resourceType" : "ValueSet",
  "id" : "07e8579f-c8f2-4b67-8ef1-e95936331dc8-9",
  "url" : "http://hl7.org/fhir/comparison/ValueSet/07e8579f-c8f2-4b67-8ef1-e95936331dc8-9",
  "name" : "IntersectionSNOMEDCTDrugTherapyStatusCodesAndSNOMEDCTDrugTherapyStatusCodes",
  "title" : "Intersection of SNOMED CT Drug Therapy Status codes  And SNOMED CT Drug Therapy Status codes ",
  "status" : "draft",
  "date" : "2025-11-05T12:15:24+00:00",
  "compose" : {
    "include" : [{
      "filter" : [{
        "property" : "concept",
        "op" : "is-a",
        "value" : "266710000"
      }]
    },
    {
      "filter" : [{
        "property" : "concept",
        "op" : "is-a",
        "value" : "410684002"
      }]
    }]
  }
}