{
  "resourceType" : "ValueSet",
  "id" : "d3c0da4b-5d25-466d-a8ec-fe505c8cee29-11",
  "url" : "http://hl7.org/fhir/comparison/ValueSet/d3c0da4b-5d25-466d-a8ec-fe505c8cee29-11",
  "name" : "UnionCondition/Problem/DiagnosisCodesAndProblemsUvIps",
  "title" : "Union of Condition/Problem/Diagnosis Codes And Problems - IPS",
  "status" : "draft",
  "date" : "2025-11-03T17:05:12+00:00",
  "jurisdiction" : [{
    "coding" : [{
      "system" : "http://unstats.un.org/unsd/methods/m49/m49.htm",
      "code" : "001",
      "display" : "World"
    }]
  }],
  "compose" : {
    "include" : [{
      "system" : "http://snomed.info/sct",
      "filter" : [{
        "property" : "concept",
        "op" : "is-a",
        "value" : "404684003"
      }]
    },
    {
      "system" : "http://snomed.info/sct",
      "concept" : [{
        "code" : "160245001",
        "display" : "No current problems or disability"
      }]
    },
    {
      "system" : "http://snomed.info/sct",
      "filter" : [{
        "property" : "concept",
        "op" : "descendent-of",
        "value" : "404684003"
      }]
    },
    {
      "system" : "http://snomed.info/sct",
      "filter" : [{
        "property" : "concept",
        "op" : "descendent-of",
        "value" : "243796009"
      }]
    },
    {
      "system" : "http://snomed.info/sct",
      "filter" : [{
        "property" : "concept",
        "op" : "descendent-of",
        "value" : "272379006"
      }]
    },
    {
      "system" : "http://snomed.info/sct",
      "filter" : [{
        "property" : "concept",
        "op" : "is-a",
        "value" : "160245001"
      }]
    }]
  }
}